steamship_langchain/__init__.py
steamship_langchain/python_splitter.py
steamship_langchain/cache/__init__.py
steamship_langchain/cache/cache.py
steamship_langchain/callbacks/__init__.py
steamship_langchain/callbacks/logging.py
steamship_langchain/chat_models/__init__.py
steamship_langchain/chat_models/openai.py
steamship_langchain/document_loaders/__init__.py
steamship_langchain/document_loaders/steamship.py
steamship_langchain/file_loaders/__init__.py
steamship_langchain/file_loaders/base.py
steamship_langchain/file_loaders/directory.py
steamship_langchain/file_loaders/github.py
steamship_langchain/file_loaders/sphinx.py
steamship_langchain/file_loaders/text.py
steamship_langchain/file_loaders/unstructured.py
steamship_langchain/file_loaders/youtube.py
steamship_langchain/llms/__init__.py
steamship_langchain/llms/openai.py
steamship_langchain/memory/__init__.py
steamship_langchain/memory/chat_memory.py
steamship_langchain/tools/__init__.py
steamship_langchain/tools/search_tool.py
steamship_langchain/vectorstores/__init__.py
steamship_langchain/vectorstores/steamship_vector_store.py
steamship_langchain-0.0.26.dist-info/AUTHORS.rst
steamship_langchain-0.0.26.dist-info/LICENSE
steamship_langchain-0.0.26.dist-info/METADATA
steamship_langchain-0.0.26.dist-info/WHEEL
steamship_langchain-0.0.26.dist-info/top_level.txt
steamship_langchain-0.0.26.dist-info/RECORD
