Metadata-Version: 2.1
Name: steamship-langchain
Version: 0.0.26
Summary: The fastest way to deploy a production langchain API.
Project-URL: Homepage, https://steamship.com/
License-File: LICENSE
License-File: AUTHORS.rst
Requires-Dist: steamship ~=2.17.4
Requires-Dist: langchain ==0.0.200
